utilisys/__init__.py
utilisys/utilisys.py
utilisys-0.1.4.dist-info/LICENSE
utilisys-0.1.4.dist-info/METADATA
utilisys-0.1.4.dist-info/WHEEL
utilisys-0.1.4.dist-info/top_level.txt
utilisys-0.1.4.dist-info/RECORD
