Metadata-Version: 2.1
Name: utilisys
Version: 0.1.4
Summary: A collection of utility functions for various tasks by Lifsys, Inc
Home-page: https://github.com/lifsys/utilisys
Author: Lifsys, Inc
Author-email: info@lifsys.com
Classifier: Development Status :: 3 - Alpha
Classifier: Intended Audience :: Developers
Classifier: License :: OSI Approved :: MIT License
Classifier: Operating System :: OS Independent
Classifier: Programming Language :: Python :: 3
Classifier: Programming Language :: Python :: 3.7
Classifier: Programming Language :: Python :: 3.8
Classifier: Programming Language :: Python :: 3.9
Classifier: Programming Language :: Python :: 3.10
Classifier: Programming Language :: Python :: 3.11
Requires-Python: >=3.7
License-File: LICENSE
Requires-Dist: phonenumbers
Requires-Dist: pandas
Requires-Dist: redis
Requires-Dist: fuzzywuzzy
Requires-Dist: requests
Requires-Dist: beautifulsoup4
Requires-Dist: urllib3
Requires-Dist: onepasswordconnectsdk
Requires-Dist: sqlalchemy
